athina/__init__.py
athina/cli/__init__.py
athina/cli/cli.py
athina/constants.py
athina/errors/__init__.py
athina/errors/exceptions.py
athina/errors/messages.py
athina/evals/__init__.py
athina/evals/llm/__init__.py
athina/evals/llm/context_contains_enough_information/__init__.py
athina/evals/llm/context_contains_enough_information/evaluator.py
athina/evals/llm/context_contains_enough_information/examples.py
athina/evals/llm/custom_grader/__init__.py
athina/evals/llm/custom_grader/evaluator.py
athina/evals/llm/does_response_answer_query/__init__.py
athina/evals/llm/does_response_answer_query/evaluator.py
athina/evals/llm/does_response_answer_query/examples.py
athina/evals/llm/example.py
athina/evals/llm/faithfulness/__init__.py
athina/evals/llm/faithfulness/evaluator.py
athina/evals/llm/faithfulness/examples.py
athina/evals/llm/llm_evaluator.py
athina/helpers/__init__.py
athina/helpers/config.py
athina/helpers/eval_helper.py
athina/helpers/json.py
athina/helpers/kwparser.py
athina/helpers/loader_helper.py
athina/helpers/logger.py
athina/helpers/package_helper.py
athina/helpers/run_helper.py
athina/interfaces/__init__.py
athina/interfaces/athina.py
athina/interfaces/model.py
athina/interfaces/result.py
athina/keys/__init__.py
athina/keys/athina_api_key.py
athina/keys/openai_api_key.py
athina/llms/__init__.py
athina/llms/openai_service.py
athina/loaders/__init__.py
athina/loaders/loader.py
athina/loaders/rag_loader.py
athina/loaders/response_loader.py
athina/runner/__init__.py
athina/runner/run.py
athina/services/athina_api_service.py
athina_evals-0.0.3.dist-info/METADATA
athina_evals-0.0.3.dist-info/WHEEL
athina_evals-0.0.3.dist-info/entry_points.txt
athina_evals-0.0.3.dist-info/RECORD
